LMRRfactory/__init__.py
LMRRfactory/generate.py
LMRRfactory/thirdbodydatabase.yaml
lmrrfactory-1.0.8.dist-info/METADATA
lmrrfactory-1.0.8.dist-info/WHEEL
lmrrfactory-1.0.8.dist-info/top_level.txt
lmrrfactory-1.0.8.dist-info/RECORD
