Metadata-Version: 2.4
Name: LMRRfactory
Version: 1.0.8
Summary: Auto-generate LMR-R reactions and mechanisms
Author-email: Patrick Singal <p.singal@columbia.edu>
License: MIT
Project-URL: Homepage, https://github.com/TheBurkeLab/LMRRfactory
Requires-Python: >=3.8
